LICENCE
MANIFEST.in
README.rst
setup.py
tests/test_gp_interp.py
tests/test_hyp_search.py
tests/test_kernels.py
tests/test_meanify.py
treegp/__init__.py
treegp/_version.py
treegp/gp_interp.py
treegp/kernels.py
treegp/log_likelihood.py
treegp/meanify.py
treegp/powerSpectrum.py
treegp/two_pcf.py
treegp/utils.py
treegp.egg-info/PKG-INFO
treegp.egg-info/SOURCES.txt
treegp.egg-info/dependency_links.txt
treegp.egg-info/requires.txt
treegp.egg-info/top_level.txt