Metadata-Version: 2.1
Name: treegp
Version: 1.4.0
Summary: treegp
Home-page: https://github.com/PFLeget/treegp
Download-URL: https://github.com/PFLeget/treegp/releases/tag/v1.4.0.zip
Author: PFLeget
License: BSD License
Classifier: Topic :: Scientific/Engineering :: Astronomy
Classifier: Intended Audience :: Science/Research
License-File: LICENCE
Requires-Dist: numpy
Requires-Dist: scipy
Requires-Dist: treecorr>=4.2
Requires-Dist: fitsio>=0.9.12
Requires-Dist: scikit-learn>=0.18
Requires-Dist: iminuit>2
